{"symbol":"SHOP","provider":"yahoo-finance","fetchedAt":"2025-12-22T21:07:42.231Z","asOfDate":"2025-12-22","articles":[{"id":"8ece047f-2525-3140-b677-00167c02d591","title":"Gen Z Isn’t Done with Fashion; Just Editing It, Depop Reports","url":"https://finance.yahoo.com/m/8ece047f-2525-3140-b677-00167c02d591/gen-z-isn%E2%80%99t-done-with.html","publisher":"Sourcing Journal","publishedAt":"2025-12-22T20:26:43.000Z","relatedTickers":[],"mainIdea":"Gen Z Isn’t Done with Fashion; Just Editing It, Depop Reports","summary":"Sourcing Journal: Depop has dropped “The Edited Self,” a 2026 trends forecast that predicts a major shift toward intentional and personalized fashion among re-shoppers."},{"id":"994b608c-8bb5-382e-b200-47f3eedb88c4","title":"See list of 11 recalled products sold at Walmart, Amazon","url":"https://finance.yahoo.com/m/994b608c-8bb5-382e-b200-47f3eedb88c4/see-list-of-11-recalled.html","publisher":"USA TODAY","publishedAt":"2025-12-22T20:20:12.000Z","relatedTickers":[],"mainIdea":"See list of 11 recalled products sold at Walmart, Amazon","summary":"USA TODAY: Eleven products sold at Walmart and Amazon were recalled for various safety concerns on Dec. 18."},{"id":"437785bd-4d12-377c-80a9-462a3d93dc7e","title":"Can Shopify (SHOP) Turn Agentic AI and Sustainability Bets Into Durable Platform Advantage?","url":"https://finance.yahoo.com/news/shopify-shop-turn-agentic-ai-200749018.html","publisher":"Simply Wall St.","publishedAt":"2025-12-22T20:07:49.000Z","relatedTickers":[],"mainIdea":"Can Shopify (SHOP) Turn Agentic AI and Sustainability Bets Into Durable Platform Advantage?","summary":"Simply Wall St.: Over the past week, Shopify has been in focus as analysts highlighted its push into AI-enabled “agentic commerce,” new Winter ’26 Edition tools, and enhanced partnerships like the Contentsquare analytics tie-up, while broader industry attention also touched on regulatory actions affecting merchants selling medical‑grade products online. At the same time, Shopify’s growing role in AI-powered commerce infrastructure and its support for initiatives such as Frontier’s long-term carbon removal..."}]}
