{"symbol":"NVDA","provider":"yahoo-finance","fetchedAt":"2025-12-22T21:07:42.231Z","asOfDate":"2025-12-22","articles":[{"id":"1ffa91d0-d4ae-3015-9b44-280eba8c1484","title":"Update: Market Chatter: Nvidia to Start Shipping H200 AI Chips to Chinese Customers by Mid-February","url":"https://finance.yahoo.com/news/market-chatter-nvidia-start-shipping-185424578.html","publisher":"MT Newswires","publishedAt":"2025-12-22T18:54:24.000Z","relatedTickers":[],"mainIdea":"Update: Market Chatter: Nvidia to Start Shipping H200 AI Chips to Chinese Customers by Mid-February","summary":"MT Newswires: (Updates with statement from Nvidia in fifth paragraph.) Nvidia (NVDA) has told Chinese customers"},{"id":"14a6d55a-9817-34ab-b98a-025484498c90","title":"As Nvidia Acquires SchedMD, Should You Buy, Sell, or Hold NVDA Stock?","url":"https://finance.yahoo.com/m/14a6d55a-9817-34ab-b98a-025484498c90/as-nvidia-acquires-schedmd%2C.html","publisher":"Barchart","publishedAt":"2025-12-22T17:45:13.000Z","relatedTickers":[],"mainIdea":"As Nvidia Acquires SchedMD, Should You Buy, Sell, or Hold NVDA Stock?","summary":"Barchart: Nvidia’s acquisition of SchedMD is strengthening its AI and computing capabilities."},{"id":"4e22d838-b965-3a3f-9e48-a38ce6e0f6d0","title":"‘NVIDIA (NVDA)’s a Mark Time Stock Right Now,” Says Jim Cramer","url":"https://finance.yahoo.com/news/nvidia-nvda-mark-time-stock-173107598.html","publisher":"Insider Monkey","publishedAt":"2025-12-22T17:31:07.000Z","relatedTickers":[],"mainIdea":"‘NVIDIA (NVDA)’s a Mark Time Stock Right Now,” Says Jim Cramer","summary":"Insider Monkey: We recently published 8 Stocks on Jim Cramer’s Radar. NVIDIA Corporation (NASDAQ:NVDA) is one of the stocks on Jim Cramer’s radars. NVIDIA Corporation (NASDAQ:NVDA)’s shares haven’t performed well lately. They are up by 30.9% year-to-date, but since October end, the stock is down by 12.6% amidst worries about an AI bubble and competition in the […]"}]}
